<?xml version="1.0" encoding="UTF-8"?>
<!DOCTYPE mapper PUBLIC "-//mybatis.org//DTD Mapper 3.0//EN" "http://mybatis.org/dtd/mybatis-3-mapper.dtd">
<mapper namespace="com.example.lfm.dao.ActPrintMapper">
  <resultMap id="BaseResultMap" type="com.example.lfm.entity.ActPrint">
    <!--
      WARNING - @mbg.generated
      This element is automatically generated by MyBatis Generator, do not modify.
    -->
    <id column="print_id" jdbcType="BIGINT" property="printId" />
    <result column="student_id" jdbcType="BIGINT" property="studentId" />
    <result column="file_name" jdbcType="VARCHAR" property="fileName" />
    <result column="file_url" jdbcType="VARCHAR" property="fileUrl" />
    <result column="user_print_id" jdbcType="BIGINT" property="userPrintId" />
    <result column="user_delivery_id" jdbcType="BIGINT" property="userDeliveryId" />
    <result column="print_number" jdbcType="INTEGER" property="printNumber" />
    <result column="both_side_flag" jdbcType="CHAR" property="bothSideFlag" />
    <result column="color_flag" jdbcType="CHAR" property="colorFlag" />
    <result column="sealing_flag" jdbcType="CHAR" property="sealingFlag" />
    <result column="cover_flag" jdbcType="CHAR" property="coverFlag" />
    <result column="paper_size" jdbcType="VARCHAR" property="paperSize" />
    <result column="student_remark" jdbcType="VARCHAR" property="studentRemark" />
    <result column="status" jdbcType="CHAR" property="status" />
    <result column="address_id" jdbcType="BIGINT" property="addressId" />
    <result column="cover_color" jdbcType="CHAR" property="coverColor" />
    <result column="fee" jdbcType="DOUBLE" property="fee" />
    <result column="pay_time" jdbcType="TIMESTAMP" property="payTime" />
    <result column="print_time" jdbcType="TIMESTAMP" property="printTime" />
    <result column="delivery_time" jdbcType="TIMESTAMP" property="deliveryTime" />
    <result column="finish_time" jdbcType="TIMESTAMP" property="finishTime" />
    <result column="create_by" jdbcType="VARCHAR" property="createBy" />
    <result column="create_time" jdbcType="TIMESTAMP" property="createTime" />
    <result column="update_by" jdbcType="VARCHAR" property="updateBy" />
    <result column="update_time" jdbcType="TIMESTAMP" property="updateTime" />
    <result column="remark" jdbcType="VARCHAR" property="remark" />
  </resultMap>
  <delete id="deleteByPrimaryKey" parameterType="java.lang.Long">
    <!--
      WARNING - @mbg.generated
      This element is automatically generated by MyBatis Generator, do not modify.
    -->
    delete from act_print
    where print_id = #{printId,jdbcType=BIGINT}
  </delete>
  <insert id="insert" parameterType="com.example.lfm.entity.ActPrint">
    <!--
      WARNING - @mbg.generated
      This element is automatically generated by MyBatis Generator, do not modify.
    -->
    insert into act_print (print_id, student_id, file_name, 
      file_url, user_print_id, user_delivery_id, 
      print_number, both_side_flag, color_flag, 
      sealing_flag, cover_flag, paper_size, 
      student_remark, `status`, address_id, 
      cover_color, fee, pay_time, 
      print_time, delivery_time, finish_time, 
      create_by, create_time, update_by, 
      update_time, remark)
    values (#{printId,jdbcType=BIGINT}, #{studentId,jdbcType=BIGINT}, #{fileName,jdbcType=VARCHAR}, 
      #{fileUrl,jdbcType=VARCHAR}, #{userPrintId,jdbcType=BIGINT}, #{userDeliveryId,jdbcType=BIGINT}, 
      #{printNumber,jdbcType=INTEGER}, #{bothSideFlag,jdbcType=CHAR}, #{colorFlag,jdbcType=CHAR}, 
      #{sealingFlag,jdbcType=CHAR}, #{coverFlag,jdbcType=CHAR}, #{paperSize,jdbcType=VARCHAR}, 
      #{studentRemark,jdbcType=VARCHAR}, #{status,jdbcType=CHAR}, #{addressId,jdbcType=BIGINT}, 
      #{coverColor,jdbcType=CHAR}, #{fee,jdbcType=DOUBLE}, #{payTime,jdbcType=TIMESTAMP}, 
      #{printTime,jdbcType=TIMESTAMP}, #{deliveryTime,jdbcType=TIMESTAMP}, #{finishTime,jdbcType=TIMESTAMP}, 
      #{createBy,jdbcType=VARCHAR}, #{createTime,jdbcType=TIMESTAMP}, #{updateBy,jdbcType=VARCHAR}, 
      #{updateTime,jdbcType=TIMESTAMP}, #{remark,jdbcType=VARCHAR})
  </insert>
  <update id="updateByPrimaryKey" parameterType="com.example.lfm.entity.ActPrint">
    <!--
      WARNING - @mbg.generated
      This element is automatically generated by MyBatis Generator, do not modify.
    -->
    update act_print
    set student_id = #{studentId,jdbcType=BIGINT},
      file_name = #{fileName,jdbcType=VARCHAR},
      file_url = #{fileUrl,jdbcType=VARCHAR},
      user_print_id = #{userPrintId,jdbcType=BIGINT},
      user_delivery_id = #{userDeliveryId,jdbcType=BIGINT},
      print_number = #{printNumber,jdbcType=INTEGER},
      both_side_flag = #{bothSideFlag,jdbcType=CHAR},
      color_flag = #{colorFlag,jdbcType=CHAR},
      sealing_flag = #{sealingFlag,jdbcType=CHAR},
      cover_flag = #{coverFlag,jdbcType=CHAR},
      paper_size = #{paperSize,jdbcType=VARCHAR},
      student_remark = #{studentRemark,jdbcType=VARCHAR},
      `status` = #{status,jdbcType=CHAR},
      address_id = #{addressId,jdbcType=BIGINT},
      cover_color = #{coverColor,jdbcType=CHAR},
      fee = #{fee,jdbcType=DOUBLE},
      pay_time = #{payTime,jdbcType=TIMESTAMP},
      print_time = #{printTime,jdbcType=TIMESTAMP},
      delivery_time = #{deliveryTime,jdbcType=TIMESTAMP},
      finish_time = #{finishTime,jdbcType=TIMESTAMP},
      create_by = #{createBy,jdbcType=VARCHAR},
      create_time = #{createTime,jdbcType=TIMESTAMP},
      update_by = #{updateBy,jdbcType=VARCHAR},
      update_time = #{updateTime,jdbcType=TIMESTAMP},
      remark = #{remark,jdbcType=VARCHAR}
    where print_id = #{printId,jdbcType=BIGINT}
  </update>
  <select id="selectByPrimaryKey" parameterType="java.lang.Long" resultMap="BaseResultMap">
    <!--
      WARNING - @mbg.generated
      This element is automatically generated by MyBatis Generator, do not modify.
    -->
    select print_id, student_id, file_name, file_url, user_print_id, user_delivery_id, 
    print_number, both_side_flag, color_flag, sealing_flag, cover_flag, paper_size, student_remark, 
    `status`, address_id, cover_color, fee, pay_time, print_time, delivery_time, finish_time, 
    create_by, create_time, update_by, update_time, remark
    from act_print
    where print_id = #{printId,jdbcType=BIGINT}
  </select>
  <select id="selectByStudentId" parameterType="java.lang.Long" resultMap="BaseResultMap">
    <!--
      WARNING - @mbg.generated
      This element is automatically generated by MyBatis Generator, do not modify.
    -->
    select print_id, student_id, file_name, file_url, user_print_id, user_delivery_id,
    print_number, both_side_flag, color_flag, sealing_flag, cover_flag, paper_size, student_remark,
    `status`, address_id, cover_color, fee, pay_time, print_time, delivery_time, finish_time,
    create_by, create_time, update_by, update_time, remark
    from act_print
    where student_id = #{studentId,jdbcType=BIGINT}
  </select>
  <select id="selectBySIdStatus"  resultMap="BaseResultMap">
    <!--
      WARNING - @mbg.generated
      This element is automatically generated by MyBatis Generator, do not modify.
    -->
    select print_id, student_id, file_name, file_url, user_print_id, user_delivery_id,
    print_number, both_side_flag, color_flag, sealing_flag, cover_flag, paper_size, student_remark,
    `status`, address_id, cover_color, fee, pay_time, print_time, delivery_time, finish_time,
    create_by, create_time, update_by, update_time, remark
    from act_print
    where student_id = #{studentId,jdbcType=BIGINT} and status =#{status,jdbcType=CHAR}
  </select>
  <select id="selectAll" resultMap="BaseResultMap">
    <!--
      WARNING - @mbg.generated
      This element is automatically generated by MyBatis Generator, do not modify.
    -->
    select print_id, student_id, file_name, file_url, user_print_id, user_delivery_id, 
    print_number, both_side_flag, color_flag, sealing_flag, cover_flag, paper_size, student_remark, 
    `status`, address_id, cover_color, fee, pay_time, print_time, delivery_time, finish_time, 
    create_by, create_time, update_by, update_time, remark
    from act_print
  </select>
</mapper>